bigeye_airflow/__init__.py
bigeye_airflow/models/__init__.py
bigeye_airflow/models/configurations.py
bigeye_airflow/operators/__init__.py
bigeye_airflow/operators/create_metric_operator.py
bigeye_airflow/operators/run_metrics_operator.py
bigeye_airflow/tests/__init__.py
bigeye_airflow/tests/functions/__init__.py
bigeye_airflow/tests/functions/test_metadata_functions.py
bigeye_airflow1-0.0.28.dist-info/LICENSE
bigeye_airflow1-0.0.28.dist-info/METADATA
bigeye_airflow1-0.0.28.dist-info/WHEEL
bigeye_airflow1-0.0.28.dist-info/top_level.txt
bigeye_airflow1-0.0.28.dist-info/RECORD
