Metadata-Version: 2.1
Name: bigeye-airflow1
Version: 0.0.28
Summary: Airflow operators to be used with Bigeye.  Supporting Airflow version 1.10.15.
Home-page: UNKNOWN
Author: Bigeye
Author-email: support@bigeye.com
License: Proprietary
Platform: UNKNOWN
Classifier: Programming Language :: Python :: 3
Classifier: License :: Other/Proprietary License
Classifier: Operating System :: OS Independent
Requires-Python: >=3.6,<3.10
License-File: LICENSE
Requires-Dist: apache-airflow (==1.10.15)
Requires-Dist: setuptools (~=57.0.0)
Requires-Dist: MarkupSafe (==2.0.1)
Requires-Dist: WTForms (==2.3.3)
Requires-Dist: SQLAlchemy (==1.3.20)
